README.rst
setup.py
linear/__init__.py
linear/version.py
linear.egg-info/PKG-INFO
linear.egg-info/SOURCES.txt
linear.egg-info/dependency_links.txt
linear.egg-info/top_level.txt