Metadata-Version: 1.1
Name: linear
Version: 0.0.dev0
Summary: A straightforward package for linear regression with Gaussian priors.
Home-page: https://barentsen.github.io/linear/
Author: Geert Barentsen
Author-email: hello@geert.io
License: BSD
Platform: UNKNOWN
Classifier: Development Status :: 5 - Production/Stable
Classifier: License :: OSI Approved :: MIT License
Classifier: Operating System :: OS Independent
Classifier: Programming Language :: Python
Classifier: Intended Audience :: Science/Research
Classifier: Topic :: Scientific/Engineering :: Astronomy
